pdwrapper/__init__.py
pdwrapper/pdwrapper.py
pdwrapper-0.0.14.dist-info/LICENSE
pdwrapper-0.0.14.dist-info/METADATA
pdwrapper-0.0.14.dist-info/WHEEL
pdwrapper-0.0.14.dist-info/entry_points.txt
pdwrapper-0.0.14.dist-info/top_level.txt
pdwrapper-0.0.14.dist-info/RECORD
