Metadata-Version: 2.1
Name: pdwrapper
Version: 0.0.14
Summary: Script used inside nx targets for deploying services
Home-page: UNKNOWN
Author: Butler Hospitality
License: MIT license
Keywords: pdwrapper
Platform: UNKNOWN
Requires-Python: >=3.6
License-File: LICENSE
Requires-Dist: click (==8.0.4)
Requires-Dist: python-dotenv (==0.19.2)
Requires-Dist: boto3 (==1.20.37)
Requires-Dist: botocore (==1.23.37)
Requires-Dist: pyyaml (==5.4)
Requires-Dist: jsonschema (==2.5.1)
